tidyfiles/__init__.py
tidyfiles/cli.py
tidyfiles/config.py
tidyfiles/history.py
tidyfiles/logger.py
tidyfiles/operations.py
tidyfiles/security.py
tidyfiles-0.12.1.dist-info/METADATA
tidyfiles-0.12.1.dist-info/WHEEL
tidyfiles-0.12.1.dist-info/entry_points.txt
tidyfiles-0.12.1.dist-info/licenses/LICENSE
tidyfiles-0.12.1.dist-info/RECORD
