Metadata-Version: 2.4
Name: tidyfiles
Version: 0.12.1
Summary: TidyFiles is a user-friendly, lightweight CLI tool designed to bring order to your Downloads (or any other) folder! It intelligently organizes files by type and keep logs of all the sorting magic.
Project-URL: Homepage, https://github.com/RYZHAIEV-SERHII/TidyFiles
Project-URL: Documentation, https://github.com/RYZHAIEV-SERHII/TidyFiles#readme
Project-URL: Repository, https://github.com/RYZHAIEV-SERHII/TidyFiles.git
Project-URL: Issues, https://github.com/RYZHAIEV-SERHII/TidyFiles/issues
Author-email: Serhii Ryzhaiev <serhii.ryzhaiev@gmail.com>
License: MIT
License-File: LICENSE
Requires-Python: >=3.10
Requires-Dist: click==8.1.8
Requires-Dist: loguru==0.7.3
Requires-Dist: rich==13.9.4
Requires-Dist: shellingham==1.5.4
Requires-Dist: toml==0.10.2
Requires-Dist: typer==0.15.2
Provides-Extra: dev
Requires-Dist: cfgv==3.4.0; extra == 'dev'
Requires-Dist: distlib==0.3.9; extra == 'dev'
Requires-Dist: filelock==3.18.0; extra == 'dev'
Requires-Dist: identify==2.6.9; extra == 'dev'
Requires-Dist: markdown-it-py==3.0.0; extra == 'dev'
Requires-Dist: mdurl==0.1.2; extra == 'dev'
Requires-Dist: nodeenv==1.9.1; extra == 'dev'
Requires-Dist: pip==25.0.1; extra == 'dev'
Requires-Dist: platformdirs==4.3.6; extra == 'dev'
Requires-Dist: pre-commit==4.1.0; extra == 'dev'
Requires-Dist: pygments==2.19.1; extra == 'dev'
Requires-Dist: python-semantic-release>=9.21.0; extra == 'dev'
Requires-Dist: pyyaml==6.0.2; extra == 'dev'
Requires-Dist: ruff==0.11.0; extra == 'dev'
Requires-Dist: typing-extensions==4.12.2; extra == 'dev'
Requires-Dist: virtualenv==20.29.3; extra == 'dev'
Provides-Extra: test
Requires-Dist: iniconfig==2.0.0; extra == 'test'
Requires-Dist: packaging==24.2; extra == 'test'
Requires-Dist: pluggy==1.5.0; extra == 'test'
Requires-Dist: pytest-cov>=6.0.0; extra == 'test'
Requires-Dist: pytest==8.3.5; extra == 'test'
